python_fcm/__init__.py
python_fcm/fcm.py
python_fcm-0.1.dist-info/DESCRIPTION.rst
python_fcm-0.1.dist-info/METADATA
python_fcm-0.1.dist-info/RECORD
python_fcm-0.1.dist-info/WHEEL
python_fcm-0.1.dist-info/metadata.json
python_fcm-0.1.dist-info/top_level.txt
