Metadata-Version: 2.0
Name: python-fcm
Version: 0.1
Summary: Simple FCM notification
Home-page: http://github.com/vipin08/python_fcm
Author: Vipin Kumar
Author-email: vpnkumar.kumar1@gmail.com
License: MIT
Platform: UNKNOWN
Classifier: Development Status :: 3 - Alpha
Classifier: License :: OSI Approved :: MIT License
Classifier: Programming Language :: Python :: 2.7
Classifier: Topic :: Text Processing :: Linguistic
